wprime/wprime.py
wprime-1.0.dist-info/LICENSE
wprime-1.0.dist-info/METADATA
wprime-1.0.dist-info/WHEEL
wprime-1.0.dist-info/top_level.txt
wprime-1.0.dist-info/RECORD
